es_builder/__init__.py
es_builder/es_model.py
es_builder/query_builder.py
es_builder/utils.py
esBuilder-0.0.1.dist-info/METADATA
esBuilder-0.0.1.dist-info/WHEEL
esBuilder-0.0.1.dist-info/top_level.txt
esBuilder-0.0.1.dist-info/RECORD
