Metadata-Version: 2.1
Name: esBuilder
Version: 0.0.1
Summary: ez to use elasticSearch
Home-page: https://github.com/sl40/esBuilder
Author: silin
Author-email: silinwork@gmail.com
License: UNKNOWN
Platform: UNKNOWN
Classifier: Programming Language :: Python :: 3
Classifier: License :: OSI Approved :: MIT License
Classifier: Operating System :: OS Independent
